{
  "_id": "kCO4r8NOm8E2T3eH",
  "folder": "eecAsQsyAvctWUww",
  "img": "icons/sundries/books/book-red-exclamation.webp",
  "name": "Nimble Faerefolk",
  "system": {
    "actionType": {
      "value": "passive"
    },
    "actions": {
      "value": null
    },
    "category": "ancestry",
    "description": {
      "value": "<p>Your muscles are tightly honed. Your Speed increases by 5 feet.</p>",
      "gm": ""
    },
    "level": {
      "value": 1
    },
    "prerequisites": {
      "value": []
    },
    "publication": {
      "license": "ORC",
      "remaster": true,
      "title": "Aedenir Homebrew",
      "authors": ""
    },
    "rules": [
      {
        "key": "FlatModifier",
        "selector": "land-speed",
        "value": 5
      }
    ],
    "traits": {
      "rarity": "common",
      "value": [
        "faerefolk"
      ],
      "otherTags": []
    },
    "slug": "nimble-faerefolk",
    "_migration": {
      "version": 0.955,
      "previous": null
    },
    "onlyLevel1": false,
    "maxTakable": 1,
    "subfeatures": {
      "proficiencies": {},
      "senses": {},
      "suppressedFeatures": []
    },
    "location": null
  },
  "type": "feat",
  "_stats": {
    "coreVersion": "14.360",
    "systemId": "pf2e",
    "systemVersion": "8.0.2",
    "createdTime": 1776800298502,
    "modifiedTime": 1777061548878,
    "exportSource": null,
    "compendiumSource": "Compendium.undefined.aedenir-homebrew-featsfeatures.Item.kCO4r8NOm8E2T3eH",
    "duplicateSource": null
  },
  "effects": [],
  "ownership": {
    "default": 0
  },
  "flags": {},
  "sort": 2100000,
  "_key": "!items!kCO4r8NOm8E2T3eH"
}
